Workbook

Sheet INVOICE
A1: CALIFOR UPHOLSTERY MATERIALS CO., LTD.
A2: XIN BAVET SEZ, Road No. 316A, Trapeang Bon and Prey Kokir Villages, Prey Kokir Commune, Chantrea District,
A3: Svay Rieng Province, Kingdom of Cambodia.
A4: VAT:L001-901903209
A5: Tel: +855 975910636
A7: INVOICE
A8: RefNo.: | B8: ='PACKING LIST'!B7
A9: Invoice No: | B9: ='PACKING LIST'!B8
A10: Date: | B10: ='PACKING LIST'!B9
A11: To: | B11: WANEK FURNITURE CO., LTD
B12: Lot D_5A_CN, D_5C_CN, D_5E_CN, My Phuoc 3 Industrial Park,
B13: Thoi Hoa Ward, Ho Chi Minh City, Vietnam.
A14: From : | B14: ='Detail packing list'!B13
A15: To : | B15: HO CHI MINH, VIET NAM.
A16: Payment Term: | B16: ='Detail packing list'!B15
A17: Origin of goods: | B17: ='Detail packing list'!B16
A18: Shipping term: | B18: ='Detail packing list'!B17
A19: Shipped Per: | B19: BY TRUCK FROM BAVET, SVAY RIENG, CAMBODIA TO HO CHI MINH, VIETNAM.
A24: PO number | B24: Item No. | C24: Description of Goods | D24: Quantity | E24: Unit | F24: Unit Price (USD) | G24: Amount (USD)
B25: 140522 | C25: PT2C496 | D25: 51399.2 | F25: 1.42 | G25: =D25 * F25
B26: 140478 | C26: PT2DT21 | D26: 42301.4 | F26: 0.86 | G26: =D26 * F26
B27: 140488 | C27: PT2F060 | D27: 3622.1 | F27: 0.86 | G27: =D27 * F27
B28: 140478 | C28: PT2F252 | D28: 56246.6 | F28: 0.86 | G28: =D28 * F28
B29: 140478 | C29: PT2F262 | D29: 62114 | F29: 0.86 | G29: =D29 * F29
C30: TOTAL | D30: =SUM(D25:D29) | G30: =SUM(G25:G29)
A34: =A1

Sheet Detail packing list
A1: CALIFOR UPHOLSTERY MATERIALS CO., LTD.
A2: XIN BAVET SEZ, Road No. 316A, Trapeang Bon and Prey Kokir Villages, Prey Kokir Commune, Chantrea District,
A3: Svay Rieng Province, Kingdom of Cambodia.
A4: VAT:L001-901903209
A5: Tel: +855 975910636
A6: DETAIL PACKING LIST
A7: RefNo.: | B7: CLF2026-062
A8: Invoice No | B8: CLW26009
A9: Date | B9: 2026-02-10 00:00:00
A10: To | B10: =INVOICE!B11
B11: Lot D_5A_CN, D_5C_CN, D_5E_CN, My Phuoc 3 Industrial Park,
B12: Thoi Hoa Ward, Ho Chi Minh City, Vietnam.
A13: From | B13: BAVET, SVAY RIENG, CAMBODIA
A14: To | B14: =INVOICE!B15
A15: Payment Term: | B15: T/T 43 days B/L date
A16: Origin of goods: | B16: CAMBODIA
A17: Shipping term: | B17: DAP: HCM
A21: PO number | B21: Item No. | C21: Description of Goods | D21: PALLET NO.# | E21: PCS | F21: Quantity (SF) | G21: Unit | H21: Net Weight (Kgs) | I21: Gross Weight (Kgs) | J21: Volume (CBM) | K21: Container number | L21: Remark
B22: 140522 | C22: PT2C496 | D22: 1 | E22: 225 | F22: 11135.1 | G22: 1.42 | H22: 865.5 | I22: 910.5 | J22: 2.8116 | K22: 1
B23: 140522 | C23: PT2C496 | D23: 1 | E23: 216 | F23: 10508.5 | G23: 1.42 | H23: 800.5263 | I23: 843.1579 | J23: 2.401 | K23: 2
B24: 140522 | C24: PT2C496 | D24: 0 | E24: 12 | F24: 432.6 | G24: 1.42 | H24: 44.4737 | I24: 46.8421 | J24: 0.1334 | K24: 3
B25: 140522 | C25: PT2C496 | D25: 1 | E25: 225 | F25: 11165.8 | G25: 1.42 | H25: 871 | I25: 916 | J25: 2.5344 | K25: 4
B26: 140522 | C26: PT2C496 | D26: 1 | E26: 225 | F26: 11087.3 | G26: 1.42 | H26: 868.5 | I26: 913.5 | J26: 2.5344 | K26: 5
B27: 140522 | C27: PT2C496 | D27: 1 | E27: 73 | F27: 3607.4 | G27: 1.42 | H27: 276 | I27: 298.5 | J27: 1.0296 | K27: 6
B28: 140522 | C28: PT2C496 | D28: 0 | E28: 1 | F28: 36.7 | G28: 1.42 | H28: 3.7808 | I28: 4.089 | J28: 0.0141 | K28: 7
B29: 140522 | C29: PT2C496 | D29: 0 | E29: 72 | F29: 3425.8 | G29: 1.42 | H29: 272.2192 | I29: 294.411 | J29: 1.0155 | K29: 8
B30: 140478 | C30: PT2DT21 | D30: 1 | E30: 280 | F30: 10166.2 | G30: 0.86 | H30: 747.5 | I30: 792.5 | J30: 2.4948 | K30: 9
B31: 140478 | C31: PT2DT21 | D31: 1 | E31: 275 | F31: 10015 | G31: 0.86 | H31: 747 | I31: 792 | J31: 2.7324 | K31: 10
B32: 140478 | C32: PT2DT21 | D32: 1 | E32: 171 | F32: 6201.2 | G32: 0.86 | H32: 462 | I32: 507 | J32: 1.9404 | K32: 11
B33: 140478 | C33: PT2DT21 | D33: 1 | E33: 290 | F33: 10426.9 | G33: 0.86 | H33: 769.5 | I33: 814.5 | J33: 2.574 | K33: 12
... B56: 140478 | C56: PT2F262 | D56: 0 | E56: 37 | F56: 1209.4 | G56: 0.86 | H56: 94.4821 | I56: 114.3036 | J56: 0.6105 | K56: 35
C57: LEATHER (HS.CODE: 4107.12.00)
B58: 25 PALLETS | C58: TOTAL： | E58: =SUM(E22:E56) | F58: =SUM(F22:F56) | H58: =SUM(H22:H56) | I58: =SUM(I22:I56) | J58: =SUM(J22:J56)
A60: Warning information
A64: =A1

Sheet DeepSheet
A1: col_invoice_no | B1: col_ref_no | C1: col_date
